Workbook

Sheet Resumen_QA
A1: TABLERO DE CONTROL DE PRUEBAS (QA / UAT) — METODOLOGÍA DE IA
A2: Resumen dinámico de ejecución por Suite de Prueba. Cambia el estado en las pestañas 1 a 6 y este tablero se actualizará automáticamente.
A4: Suite de Prueba | B4: Pestaña | C4: Artefacto / Alcance | D4: Total Casos | E4: PASS | F4: FAIL | G4: PENDIENTE / BLOQ. | H4: % Aprobación
A5: Suite 1 — Estimador Estratégico | B5: 1_Estimador | C5: Estimador_Diagnostico_Estrategico.xlsx | D5: =COUNTA('1_Estimador'!A5:A10) -> 6 | E5: =COUNTIF('1_Estimador'!H5:H10,"PASS") -> 6 | F5: =COUNTIF('1_Estimador'!H5:H10,"FAIL") -> 0 | G5: =COUNTIF('1_Estimador'!H5:H10,"PENDIENTE")+COUNTIF('1_Estimador'!H5:H10,"BLOQUEADO") -> 0 | H5: =IFERROR(E5/D5,0) -> 1
A6: Suite 2 — Kits M5 (Estructura Común) | B6: 2_Kits_Comun | C6: 5 Kits Excel (Catálogo, Cuestionario, Habilitadores, Canvas) | D6: =COUNTA('2_Kits_Comun'!A5:A14) -> 10 | E6: =COUNTIF('2_Kits_Comun'!H5:H14,"PASS") -> 10 | F6: =COUNTIF('2_Kits_Comun'!H5:H14,"FAIL") -> 0 | G6: =COUNTIF('2_Kits_Comun'!H5:H14,"PENDIENTE")+COUNTIF('2_Kits_Comun'!H5:H14,"BLOQUEADO") -> 0 | H6: =IFERROR(E6/D6,0) -> 1
A7: Suite 3 — Kits M5 (Hojas Especializadas) | B7: 3_Kits_Especiales | C7: KPIs y Targets (Finanzas) + Compliance Radar (Legal) | D7: =COUNTA('3_Kits_Especiales'!A5:A9) -> 5 | E7: =COUNTIF('3_Kits_Especiales'!H5:H9,"PASS") -> 5 | F7: =COUNTIF('3_Kits_Especiales'!H5:H9,"FAIL") -> 0 | G7: =COUNTIF('3_Kits_Especiales'!H5:H9,"PENDIENTE")+COUNTIF('3_Kits_Especiales'!H5:H9,"BLOQUEADO") -> 0 | H7: =IFERROR(E7/D7,0) -> 1
A8: Suite 4 — Módulo 3 (Portafolio) | B8: 4_Modulo_3 | C8: Modulo_3_Portafolio_Innovacion.docx | D8: =COUNTA('4_Modulo_3'!A5:A9) -> 5 | E8: =COUNTIF('4_Modulo_3'!H5:H9,"PASS") -> 5 | F8: =COUNTIF('4_Modulo_3'!H5:H9,"FAIL") -> 0 | G8: =COUNTIF('4_Modulo_3'!H5:H9,"PENDIENTE")+COUNTIF('4_Modulo_3'!H5:H9,"BLOQUEADO") -> 0 | H8: =IFERROR(E8/D8,0) -> 1
A9: Suite 5 — Módulo 4 (Marco de Decisión) | B9: 5_Modulo_4 | C9: Modulo_4_Marco_Decision_IA.docx | D9: =COUNTA('5_Modulo_4'!A5:A8) -> 4 | E9: =COUNTIF('5_Modulo_4'!H5:H8,"PASS") -> 4 | F9: =COUNTIF('5_Modulo_4'!H5:H8,"FAIL") -> 0 | G9: =COUNTIF('5_Modulo_4'!H5:H8,"PENDIENTE")+COUNTIF('5_Modulo_4'!H5:H8,"BLOQUEADO") -> 0 | H9: =IFERROR(E9/D9,0) -> 1
A10: Suite 6 — Módulo 6 (Implementación y Cambio) | B10: 6_Modulo_6 | C10: Modulo_6_Implementacion_y_Cambio.docx | D10: =COUNTA('6_Modulo_6'!A5:A10) -> 6 | E10: =COUNTIF('6_Modulo_6'!H5:H10,"PASS") -> 6 | F10: =COUNTIF('6_Modulo_6'!H5:H10,"FAIL") -> 0 | G10: =COUNTIF('6_Modulo_6'!H5:H10,"PENDIENTE")+COUNTIF('6_Modulo_6'!H5:H10,"BLOQUEADO") -> 0 | H10: =IFERROR(E10/D10,0) -> 1
A11: TOTAL GENERAL DEL PLAN DE PRUEBAS | B11: 6 Pestañas | C11: 4 Módulos (.docx) + 6 Libros (.xlsx) | D11: =SUM(D5:D10) -> 36 | E11: =SUM(E5:E10) -> 36 | F11: =SUM(F5:F10) -> 0 | G11: =SUM(G5:G10) -> 0 | H11: =IFERROR(E11/D11,0) -> 1
A14: INVENTARIO DE AUDITORÍA TÉCNICA SOBRE ARCHIVOS EXCEL DEL PAQUETE
A15: Archivo Excel Auditado | B15: Pestañas Incluidas | C15: Fórmulas Activas Verificadas | D15: Reglas Data Validation | E15: Estado de Integridad
A16: Estimador_Diagnostico_Estrategico.xlsx | B16: Estimador, Escenarios, Factores (3) | C16: 87 | D16: 6 listas desplegables | E16: 100% OK — Sin errores #REF! ni #N/A
A17: Kit_Finanzas_Administracion.xlsx | B17: Catálogo, Cuestionario, Canvas, Habilitadores, KPIs y Targets (5) | C17: 35 | D17: 3 bloques validados | E17: 100% OK — Uplift reducción/incremento exacto
A18: Kit_Legal_Compliance.xlsx | B18: Compliance Radar, Catálogo, Cuestionario, Canvas, Tabla Maestra (5) | C18: 34 | D18: 4 bloques validados | E18: 100% OK — 26 VLOOKUP en 12 países exactos
A19: Kit_Marketing_DemandGen_B2B.xlsx | B19: Catálogo, Cuestionario, Canvas, Habilitadores (4) | C19: 19 | D19: 3 bloques validados | E19: 100% OK — Matriz Pain × Readiness exacta
A20: Kit_Operaciones_Planta_PYME.xlsx | B20: Catálogo, Cuestionario, Canvas, Habilitadores (4) | C20: 14 | D20: 3 bloques validados | E20: 100% OK — Umbrales planta (80/60/40%) exactos
A21: Kit_Ventas_B2B.xlsx | B21: Catálogo, Cuestionario, Canvas, Sales Stack Maturity (4) | C21: 14 | D21: 3 bloques validados | E21: 100% OK — Umbrales Sales Stack exactos

Sheet 1_Estimador
A1: SUITE 1: ESTIMADOR DE DIAGNÓSTICO ESTRATÉGICO
A2: Archivo bajo prueba: Estimador_Diagnostico_Estrategico.xlsx (Pestañas Estimador, Escenarios y Factores)
A4: ID Caso | B4: Componente / Referencia | C4: Tipo de Prueba | D4: Prioridad | E4: Objetivo de la Prueba | F4: Datos de Entrada / Pasos de Ejecución | G4: Resultado Esperado | H4: Estado (QA) | I4: Observaciones / Evidencia
A5: TC-EST-01 | B5: Hoja 'Estimador' (Celdas B7:F29, B33:B36) | C5: Funcional / Cálculo | D5: Crítica | E5: Verificar el cálculo base de esfuerzo y costo para un cliente típico (mediano, sector estándar, madurez intermedia) sin factores adicionales. | F5: 1. En B7 seleccionar 'Mediana (200-2.000 colaboradores)' 2. En B8: 'Estándar / no regulado' 3. En B9: 'Intermedia (2.5 - 3.4)' 4. En B10: 'Single country' 5. En B11: 'No existen' 6. En B13: 'Estándar (M1+M2+M3, 4 semanas)' 7. Verificar tarifas B20:B22 ($2000, $1200, $700). | G5: • Factores D7:D11 = 1 y Factor Combinado (D16) = 1.0 • M1 (Fila 26): 14.5 días | $19,400 USD • M2 (Fila 27): 22.5 días | $27,100 USD • M3 (Fila 28): 16.5 días | $18,550 USD • Total Días (E29 / B33) = 53.5 días (428 horas) • INVERSIÓN ESTIMADA (F29 / B36) = $65,050 USD. | H5: PASS | I5: Verificado en auditoría automatizada: cuadra 100% con pestaña Escenarios.
A6: TC-EST-02 | B6: Hoja 'Estimador' y 'Escenarios' (Modo Lite) | C6: Funcional / Regla | D6: Alta | E6: Validar que el modo Lite anule el esfuerzo y costo de los Módulos 2 y 3 aplicando factores 0. | F6: 1. Mantener parámetros de cliente típico (D16 = 1.0). 2. Cambiar B13 a 'Lite (solo M1, 4 semanas)'. 3. Revisar fila 14 y tabla de desglose (filas 26-29). | G6: • Factores por fase (E14, G14, I14): M1 = 1, M2 = 0, M3 = 0. • Días y costo de M2 y M3 = 0. • Total Días = 14.5 (Sénior 5, Manager 5.5, Analista 4) | 116 horas. • INVERSIÓN ESTIMADA = $19,400 USD (idéntico a Escenarios!B15). | H6: PASS | I6: Fórmulas VLOOKUP en E14, G14 e I14 operan sin errores.
A7: TC-EST-03 | B7: Hoja 'Estimador' y 'Escenarios' (Modo Completo) | C7: Funcional / Cálculo | D7: Alta | E7: Validar que el modo Completo aplique el factor 1.2x (+20% esfuerzo) en las 3 fases y ajuste el calendario a 6 semanas. | F7: 1. Mantener cliente típico (D16 = 1.0). 2. Cambiar B13 a 'Completo (extendido, 6 semanas)'. | G7: • Calendario base (E13 / B35) = 6 semanas. • Factores M1, M2, M3 = 1.2. • Total Días = 64.2 (Sénior 14.4, Manager 28.8, Analista 21) | 513.6 horas. • INVERSIÓN ESTIMADA = $78,060 USD (idéntico a Escenarios!D15). | H7: PASS | I7: Verificado en pestaña Estimador y Escenarios.
A8: TC-EST-04 | B8: Hoja 'Estimador' y 'Factores' (Complejidad Máxima) | C8: Valor Límite (Boundary) | D8: Alta | E8: Verificar la multiplicación encadenada en D16 (=D7*D8*D9*D10*D11) bajo el escenario de máxima complejidad posible. | F8: Seleccionar: • B7: Multinacional (>10.000 colab.) [2.5] • B8: Altamente regulado [1.3] • B9: Inicial (1.0 - 2.4) [1.1] • B10: Multi-país (4+ geografías) [1.7] • B11: No existen [1.0] • B13: Completo (6 semanas) [1.2]. | G8: • Factor combinado (D16) = 2.5 * 1.3 * 1.1 * 1.7 * 1.0 = 6.0775. • Multiplicador total con Modo Completo = 6.0775 * 1.2 = 7.293. • Total Días (E29) = 53.5 * 7.293 = 390.1755 días. • INVERSIÓN ESTIMADA (B36) = $474,409.65 USD. | H8: PASS | I8: Cálculo exacto verificado.
A9: TC-EST-05 | B9: Hoja 'Estimador' (Complejidad Mínima) | C9: Valor Límite (Boundary) | D9: Media | E9: Verificar el cálculo en el escenario de menor tamaño, mayor madurez y descuento por assessments vigentes. | F9: Seleccionar: • B7: Pequeña (<200 colab.) [0.7] • B8: Estándar [1.0] • B9: Madura (3.5 - 5.0) [0.9] • B10: Single country [1.0] • B11: Existen completos y vigentes [0.85] • B13: Estándar [1.0]. | G9: • Factor combinado (D16) = 0.7 * 1.0 * 0.9 * 1.0 * 0.85 = 0.5355. • Total Días = 53.5 * 0.5355 = 28.64925 días. • INVERSIÓN ESTIMADA = $34,834.28 USD. | H9: PASS | I9: Cálculo exacto verificado.
A10: TC-EST-06 | B10: Hoja 'Estimador' (Celdas B7:B11, B13) | C10: Validación de Datos | D10: Media | E10: Comprobar que las celdas de selección rechacen textos libres o valores fuera de las tablas de la hoja Factores. | F10: Intentar escribir manualmente 'Empresa Gigante' en B7 o 'Modo Rápido' en B13. | G10: Excel muestra ventana de error de validación de datos y bloquea el ingreso no autorizado. | H10: PASS | I10: 6 reglas DataValidation activas y verificadas.

Sheet 2_Kits_Comun
A1: SUITE 2: KITS FUNCIONALES MÓDULO 5 (ESTRUCTURA COMÚN)
A2: Archivos bajo prueba: Finanzas, Legal, Marketing, Operaciones de Planta y Ventas B2B (Catálogo, Cuestionario, Habilitadores, Canvas)
A4: ID Caso | B4: Componente / Referencia | C4: Tipo de Prueba | D4: Prioridad | E4: Objetivo de la Prueba | F4: Datos de Entrada / Pasos de Ejecución | G4: Resultado Esperado | H4: Estado (QA) | I4: Observaciones / Evidencia
A5: TC-KIT-01 | B5: Hoja 'Catálogo' (Todos los Kits M5) | C5: Funcional / Conteo | D5: Alta | E5: Verificar las fórmulas COUNTIF al pie del Catálogo que contabilizan casos marcados como 'Sí', 'Tal vez', 'No' y Total Candidatos. | F5: En la columna '¿Aplica a nosotros?' (Columna J): 1. Marcar 4 casos con 'Sí'. 2. Marcar 3 casos con 'Tal vez'. 3. Marcar 2 casos con 'No'. | G5: • Conteo 'Sí' = 4 • Conteo 'Tal vez' = 3 • Conteo 'No' = 2 (en kits que muestran fila No) • Total casos candidatos (Sí + Tal vez) = 7. | H5: PASS | I5: Fórmulas COUNTIF y validación de lista ('Sí,No,Tal vez') verificadas en los 5 kits.
A6: TC-KIT-02 | B6: Hoja 'Cuestionario' (Estado Inicial Vacío) | C6: Manejo de Errores | D6: Alta | E6: Comprobar que cuando el cuestionario está vacío no aparezcan errores #DIV/0! ni #VALUE! gracias al uso de IFERROR. | F6: Dejar en blanco las 16 respuestas del cuestionario (C9:C12, C15:C18, C21:C24, C27:C30). | G6: • Puntaje Pain = 0 ('Sin datos') • Puntaje Readiness = 0 ('Sin datos') • Recomendación muestra: 'Completa primero el cuestionario'. | H6: PASS | I6: Fórmula =IFERROR(AVERAGE(...),0) verificada en todos los kits.
A7: TC-KIT-03 | B7: Hoja 'Cuestionario' (Cuadrante Quick Win) | C7: Regla de Negocio / Límite | D7: Crítica | E7: Validar que cuando Pain >= 3.5 y Readiness >= 3.5 se emita la recomendación de QUICK WIN PRIORITARIO. | F7: 1. En Bloque A (C9:C12) ingresar: 4, 4, 3, 3 (Promedio = 3.50). 2. En Bloques B, C y D (C15:C30) ingresar: todos 4 (Promedio = 4.00). | G7: • Pain = 3.5 ('Pain ALTO') • Readiness = 4.0 ('Readiness ALTA') • Recomendación = 'QUICK WIN PRIORITARIO — Avanzar ahora'. | H7: PASS | I7: Umbral exacto >=3.5 verificado en fórmula IF(AND(...)).
A8: TC-KIT-04 | B8: Hoja 'Cuestionario' (Invertir en Habilitadores) | C8: Regla de Negocio / Límite | D8: Crítica | E8: Validar que con Pain >= 3.5 y Readiness < 3.5 el kit indique invertir primero en habilitadores / stack. | F8: 1. En Bloque A (C9:C12) ingresar: 5, 4, 4, 5 (Promedio = 4.50). 2. En Bloques B, C y D ingresar valores con promedio = 3.40. | G8: • Pain = 4.5 ('Pain ALTO') • Readiness = 3.4 ('Readiness MEDIA') • Recomendación = 'INVERTIR EN HABILITADORES...' (o 'INVERTIR EN STACK COMERCIAL PRIMERO...' en Ventas). | H8: PASS | I8: Verificado en los 5 kits funcionales.
A9: TC-KIT-05 | B9: Hoja 'Cuestionario' (Oportunidad sin Urgencia) | C9: Regla de Negocio | D9: Alta | E9: Validar que con Pain < 3.5 y Readiness >= 3.5 el kit clasifique el área como Oportunidad sin Urgencia. | F9: 1. En Bloque A ingresar: 3, 3, 3, 4 (Promedio = 3.25). 2. En Bloques B, C y D ingresar todos 4 (Promedio = 4.00). | G9: • Pain = 3.25 ('Pain MEDIO') • Readiness = 4.0 ('Readiness ALTA') • Recomendación = 'OPORTUNIDAD SIN URGENCIA — Capacidad sí, pain no'. | H9: PASS | I9: Verificado en todos los kits.
A10: TC-KIT-06 | B10: Hoja 'Cuestionario' (Aún no es momento) | C10: Regla de Negocio | D10: Alta | E10: Validar que cuando tanto Pain < 3.5 como Readiness < 3.5 la recomendación sea construir capacidad antes. | F10: Ingresar puntaje 2 en las 16 preguntas del cuestionario. | G10: • Pain = 2.0 ('Pain BAJO') • Readiness = 2.0 ('Readiness BAJA') • Recomendación = 'AÚN NO ES MOMENTO — Construir capacidad antes'. | H10: PASS | I10: Verificado en todos los kits.
A11: TC-KIT-07 | B11: Hoja 'Cuestionario' (Validación 1 a 5) | C11: Validación de Datos | D11: Media | E11: Verificar que las celdas de respuesta solo acepten números enteros entre 1 y 5. | F11: Intentar ingresar 0, 6 o un decimal como 3.5 en la celda C9. | G11: Excel bloquea el ingreso (DataValidation type='whole' entre 1 y 5). | H11: PASS | I11: Regla activa en C9:C12, C15:C18, C21:C24, C27:C30.
A12: TC-KIT-08 | B12: Hoja 'Habilitadores' (Fórmula de Score y Exclusión de 'No aplica') | C12: Funcional / Cálculo | D12: Crítica | E12: Comprobar que el cálculo de readiness pondere Sí=1.0, Parcial=0.5, No=0 y excluya 'No aplica' del denominador. | F12: En los 20 habilitadores marcar: • 10 como 'Sí' • 4 como 'Parcial' • 2 como 'No' • 4 como 'No aplica'. | G12: • Total evaluables (denominador) = 10 + 4 + 2 = 16. • Puntaje ponderado (numerador) = 10 + (4 * 0.5) = 12. • Score de Readiness = 12 / 16 = 75.0% (0.75). | H12: PASS | I12: Fórmula verificada: 'No aplica' no distorsiona el denominador.
A13: TC-KIT-09 | B13: Hoja 'Habilitadores' / 'Sales Stack' (Umbrales de Recomendación) | C13: Valor Límite (Boundary) | D13: Alta | E13: Validar los cortes de recomendación según el porcentaje alcanzado en cada kit. | F13: Probar porcentajes en los límites: • Finanzas/Marketing: 70%, 40%, <40% • Operaciones/Ventas: 80%, 60%, 40%, <40%. | G13: • Finanzas/Marketing: >=70% 'READY', 40-69% 'PARCIALMENTE READY', <40% 'NO READY'. • Operaciones/Ventas: >=80% 'LISTOS para arrancar IA...', 60-79% 'LISTOS para Quick Wins...', 40-59% 'INVERTIR en paralelo...', <40% 'PRIORIDAD: cerrar 6-9 meses antes...'. | H13: PASS | I13: Fórmulas condicionales anidadas verificadas.
A14: TC-KIT-10 | B14: Hoja 'Canvas' (10 Campos Obligatorios) | C14: UAT / Documental | D14: Media | E14: Verificar en taller que el Canvas completo contenga los datos cuantificados requeridos para alimentar el Módulo 2. | F14: Revisar el llenado de los 10 bloques del Canvas para un caso seleccionado del Catálogo. | G14: • Nombre <= 8 palabras. • Costo del dolor y Magnitud del cambio cuantificados (USD/mes, horas-persona o transacciones). • Datos disponibles, familia IA hipotética, riesgos y Sponsor nominal especificados. | H14: PASS | I14: Estructura de 10 campos validada en los 5 kits.

Sheet 3_Kits_Especiales
A1: SUITE 3: HOJAS ESPECIALIZADAS (FINANZAS Y LEGAL)
A2: Archivos bajo prueba: Kit_Finanzas_Administracion.xlsx (KPIs y Targets) y Kit_Legal_Compliance.xlsx (Compliance Radar y Tabla Maestra)
A4: ID Caso | B4: Componente / Referencia | C4: Tipo de Prueba | D4: Prioridad | E4: Objetivo de la Prueba | F4: Datos de Entrada / Pasos de Ejecución | G4: Resultado Esperado | H4: Estado (QA) | I4: Observaciones / Evidencia
A5: TC-ESP-01 | B5: Kit_Finanzas — Hoja 'KPIs y Targets' (KPIs de Reducción) | C5: Funcional / Cálculo | D5: Crítica | E5: Verificar que en los KPIs donde menor es mejor (DSO, MAPE, tiempos) la fórmula de Uplift sea =(Baseline - Target)/Baseline. | F5: 1. En Caso 1 (DSO, fila 5): ingresar Baseline E5 = 60, Target F5 = 45. 2. En Caso 8 (Tiempo paquete, fila 12): ingresar Baseline E12 = 10, Target F12 = 4. | G5: • Celda G5 (=(E5-F5)/E5) calcula +25.0% de mejora/reducción. • Celda G12 (=(E12-F12)/E12) calcula +60.0% de reducción de tiempo. • Aplica correctamente a filas 5, 7, 9, 10, 12, 13, 14 y 15. | H5: PASS | I5: Inspeccionadas las 8 filas de reducción en Kit_Finanzas.
A6: TC-ESP-02 | B6: Kit_Finanzas — Hoja 'KPIs y Targets' (KPIs de Incremento) | C6: Funcional / Cálculo | D6: Crítica | E6: Verificar que en los KPIs donde mayor es mejor (tasa respuesta, % conciliado, % autocodificado, ahorro) la fórmula sea =(Target - Baseline)/Baseline. | F6: 1. En Caso 2 (Tasa respuesta, fila 6): ingresar E6 = 20%, F6 = 30%. 2. En Caso 4 (% conciliado, fila 8): ingresar E8 = 50%, F8 = 90%. | G6: • Celda G6 (=(F6-E6)/E6) calcula +50.0% de incremento. • Celda G8 (=(F8-E8)/E8) calcula +80.0% de incremento. • Aplica correctamente a filas 6, 8, 11 y 16. | H6: PASS | I6: Inspeccionadas las 4 filas de incremento en Kit_Finanzas.
A7: TC-ESP-03 | B7: Kit_Finanzas — Hoja 'KPIs y Targets' (Resumen E19:E22) | C7: Funcional / Cálculo | D7: Media | E7: Comprobar que el bloque RESUMEN cuente los casos parametrizados y promedie el Uplift y el Horizonte. | F7: Con los 4 casos cargados en TC-ESP-01 y TC-ESP-02 (Uplifts: 25%, 60%, 50%, 80%) e ingresando Horizontes H5=3, H6=3, H8=6, H12=6. | G7: • E19 (Casos con Baseline) = 4 • E20 (Casos con Target) = 4 • E21 (Uplift promedio) = 53.75% • E22 (Horizonte promedio) = 4.5 meses. | H7: PASS | I7: Fórmulas COUNT y AVERAGE verificadas.
A8: TC-ESP-04 | B8: Kit_Legal — Hoja 'Compliance Radar' y 'Tabla Maestra' | C8: Integración / VLOOKUP | D8: Crítica | E8: Validar que al cambiar el país en B5, las 26 fórmulas VLOOKUP recuperen sin error #N/A toda la normativa de la Tabla Maestra. | F8: En Compliance Radar!B5 seleccionar sucesivamente: 1. 'Chile' 2. 'Brasil' 3. 'México' 4. 'Unión Europea (referencia)'. | G8: • Chile: Ley 19.628 + Ley 21.719 (2024) | Agencia de Protección de Datos Personales (en creación). • Brasil: LGPD (Lei nº 13.709/2018) | Autoridad ANPD | Sanción 2% facturación hasta R$ 50M. • Todas las 12 jurisdicciones cargan sus 22 columnas sin #N/A. | H8: PASS | I8: 26 fórmulas VLOOKUP verificadas contra Tabla Maestra!A5:V16.
A9: TC-ESP-05 | B9: Kit_Legal — Checklist de Controles (B44:B58) | C9: Validación de Datos | D9: Media | E9: Comprobar la validación de estados en el autodiagnóstico de controles de cumplimiento. | F9: Desplegar opciones en celdas B44 a B58 de la hoja Compliance Radar. | G9: Permite seleccionar exclusivamente: 'Implementado', 'Parcial', 'Pendiente', 'No aplica'. | H9: PASS | I9: Validación de lista verificada.

Sheet 4_Modulo_3
A1: SUITE 4: MÓDULO 3 — PORTAFOLIO DE INNOVACIÓN
A2: Documento bajo prueba: Modulo_3_Portafolio_Innovacion.docx (Priorización, Horizontes H1/H2, Gobernanza, 12 Métricas y Financiamiento)
A4: ID Caso | B4: Componente / Referencia | C4: Tipo de Prueba | D4: Prioridad | E4: Objetivo de la Prueba | F4: Datos de Entrada / Pasos de Ejecución | G4: Resultado Esperado | H4: Estado (QA) | I4: Observaciones / Evidencia
A5: TC-M3-01 | B5: Módulo 3 — Sección 3.2 (Proceso de Priorización en 5 Pasos) | C5: Regla Metodológica / Cálculo | D5: Crítica | E5: Verificar la aplicación de topes máximos en la bonificación por encadenamiento (+20 máx) y penalización por concentración (-15 máx). | F5: Tomar una iniciativa candidata del Módulo 2 con Score de Valor V = 70: 1. Habilita 3 capacidades reutilizables (+10 c/u). 2. Comparte dependencia crítica con otras 4 iniciativas (-5 c/u). | G5: • Bonificación por encadenamiento = +20 puntos (aplica tope de +20 aunque 3*10 = 30). • Penalización por concentración = -15 puntos (aplica tope de -15 aunque 4*-5 = -20). • Score de Valor Ajustado = 70 + 20 - 15 = 75 puntos. | H5: PASS | I5: Regla documentada en Sección 3.2 del Módulo 3.
A6: TC-M3-02 | B6: Módulo 3 — Sección 3.1 y 3.2 (Filtro de Readiness del Área) | C6: Valor Límite (Boundary) | D6: Crítica | E6: Validar el descarte o postergación obligatoria de candidatas cuya área propietaria tenga IA-readiness <= 2.4. | F6: Evaluar 2 candidatas con alto valor (V = 88): • Candidata 1: Área con IA-readiness = 2.4. • Candidata 2: Área con IA-readiness = 2.5. | G6: • Candidata 1 (2.4): DESCARTADA / POSPUESTA hasta cerrar brecha de habilitadores. • Candidata 2 (2.5): APROBADA para asignación de horizonte. | H6: PASS | I6: Consistente entre Sección 3.1 y Paso 4 de Sección 3.2.
A7: TC-M3-03 | B7: Módulo 3 — Sección 2.3 y 3.3 (Balance H1/H2 y Concentración) | C7: Regla de Gobernanza | D7: Alta | E7: Auditar que la composición final del portafolio respete las proporciones por madurez, tope de H2 y límites por área/familia. | F7: Simular un portafolio para cliente de Madurez Inicial (Nivel 1-2 en M1) intentando: • Incluir 4 proyectos H2 simultáneos. • Concentrar 65% en GenAI y 55% en el área Comercial. | G7: Rechazo por 4 reglas de selección: 1. Madurez Inicial requiere balance recomendado de 80% Quick Wins (H1) / 20% H2. 2. Tope estricto: máximo 3 iniciativas H2 simultáneas hasta escalar la primera. 3. Máximo 50% del portafolio en una misma área propietaria. 4. Máximo 60% concentrado en una misma familia de IA. | H7: PASS | I7: Reglas verificadas en Secciones 2.3 y 3.3.
A8: TC-M3-04 | B8: Módulo 3 — Sección 5 (Tablero Ejecutivo de 12 Métricas) | C8: Umbrales de Monitoreo | D8: Alta | E8: Comprobar la activación de alertas rojas cuando las métricas de Salud (A), Valor (B) y Riesgo (C) cruzan sus umbrales críticos. | F8: Evaluar un tablero con: A1 (Paso de gates) = 45%, A3 (Adherencia comité) = 75%, A4 (Carga PMO) = 92%, B1 (Valor capturado) = 55%, B3 (Adopción) = 55%, C3 (Riesgo crítico activo) = 3, C4 (Cobertura regulatoria) = 85%. | G8: Se disparan alertas rojas con acción obligatoria para la siguiente sesión: • A1 < 50%, A3 < 80%, A4 > 90%. • B1 < 60%, B3 < 60%. • C3 > 2 iniciativas críticas sin control, C4 < 90% en sector regulado. | H8: PASS | I8: 12 métricas y umbrales verificados en Sección 5.
A9: TC-M3-05 | B9: Módulo 3 — Sección 6 y 7 (Financiamiento y Plantillas) | C9: Auditoría Documental | D9: Alta | E9: Verificar que el presupuesto anual y los Business Cases en Gate G2 cumplan los 7 principios de financiamiento. | F9: Inspeccionar el presupuesto anual del portafolio y un Business Case presentado para paso a piloto (G2). | G9: 1. Al menos 15% del presupuesto anual permanece en reserva sin asignación inicial. 2. TCO calculado a 36 meses (no solo costo de construcción). 3. 'Costo del fracaso aceptado' y umbrales de aborto explícitos en el Project Charter y Business Case. | H9: PASS | I9: Principios 1 a 7 y plantillas verificadas en Secciones 6 y 7.

Sheet 5_Modulo_4
A1: SUITE 5: MÓDULO 4 — MARCO DE DECISIÓN DE IA
A2: Documento bajo prueba: Modulo_4_Marco_Decision_IA.docx (Árbol de Decisión, Matriz Multicriterio, Reglas de Interpretación y Regulación)
A4: ID Caso | B4: Componente / Referencia | C4: Tipo de Prueba | D4: Prioridad | E4: Objetivo de la Prueba | F4: Datos de Entrada / Pasos de Ejecución | G4: Resultado Esperado | H4: Estado (QA) | I4: Observaciones / Evidencia
A5: TC-M4-01 | B5: Módulo 4 — Sección 5.2 (Árbol de Decisión de 5 Preguntas) | C5: Lógica de Decisión | D5: Crítica | E5: Comprobar que todas las bifurcaciones del árbol conduzcan a la hoja terminal (verde, ámbar o roja) correspondiente. | F5: Recorrer las 6 ramas: 1. P1=Sí -> Cambian >4/año=No 2. P1=Sí -> Cambian >4/año=Sí 3. P1=No -> P2=Parcialmente 4. P1=No -> P2=Sí -> P3=Sí 5. P1=No -> P2=No -> P4=No 6. P1=No -> P2=No -> P4=Sí -> P5=Sí. | G5: 1. Familia A (Reglas y automatización clásica) 2. Reglas + capa BPM/BRE 3. ML + reglas de respaldo (híbrido) 4. Familia B (ML supervisado / no supervisado) 5. Hoja Roja: volver a definir el problema con experto 6. Hoja Ámbar: Familia C con guardarraíles fuertes (RAG verificable, validación humana). | H5: PASS | I5: Árbol completo verificado en Sección 5.2.
A6: TC-M4-02 | B6: Módulo 4 — Sección 6.2 y 6.3 (Matriz de Scoring Multicriterio) | C6: Cálculo Matemático | D6: Crítica | E6: Verificar la fórmula Σ(puntaje_criterio × peso × afinidad) y su normalización a base 100 con el caso de referencia (Churn Telco). | F6: Evaluar el vector de 10 criterios (C1 a C10): [2, 5, 5, 3, 3, 3, 2, 4, 3, 3] con pesos [15%, 15%, 10%, 10%, 10%, 10%, 8%, 8%, 7%, 7%] contra la tabla de afinidad 6.2. | G6: • Suma ponderada cruda: - Reglas (A) = 1.99 -> Normalizado = 60 - ML clásico (B) = 2.69 -> Normalizado = 85 - GenAI (C) = 1.84 -> Normalizado = 55 • Recomendación cuantificada: Familia B (ML clásico). | H6: PASS | I6: Cálculo verificado exactamente contra Sección 6.3.
A7: TC-M4-03 | B7: Módulo 4 — Sección 6.4 (Reglas de Interpretación de Brechas) | C7: Valor Límite (Boundary) | D7: Alta | E7: Validar la regla de decisión aplicable según la diferencia de puntos entre la primera y la segunda familia. | F7: Probar 4 diferencias en base 100: • Dif = 25 pts (>20) • Dif = 14 pts (entre 10 y 20) • Dif = 6 pts (<10) • Todas las familias < 50 pts. | G7: • > 20 pts: Familia ganadora claramente correcta. • 10 a 20 pts: Ganadora recomendada, revisar criterios para posibles componentes híbridos. • < 10 pts: Solución híbrida casi segura; descomponer en sub-problemas. • Ninguna > 50 pts: No es buen candidato a IA; replantear problema. | H7: PASS | I7: Reglas verificadas en Sección 6.4.
A8: TC-M4-04 | B8: Módulo 4 — Sección 7 y 9 (Cuestionario Q1-Q18 y Salida Regulatoria) | C8: Cumplimiento / Auditoría | D8: Media | E8: Verificar que el artefacto de salida del Módulo 4 incluya la trazabilidad exigida por EU AI Act, GDPR e ISO 42001. | F8: Auditar el documento de decisión de 1-2 páginas generado al finalizar el taller del Módulo 4. | G8: Contiene: respuestas Q1-Q18, camino del árbol justificado, matriz de 10 criterios, identificación de marcos regulatorios aplicables, categoría de riesgo, obligaciones documentales (ej. DPIA) y firmas. | H8: PASS | I8: Verificado en Secciones 7.6 y 9.4.

Sheet 6_Modulo_6
A1: SUITE 6: MÓDULO 6 — IMPLEMENTACIÓN Y GESTIÓN DEL CAMBIO
A2: Documento bajo prueba: Modulo_6_Implementacion_y_Cambio.docx (Ciclo de Vida 6A, Gates G0-G5, Riesgos, Adopción 6B, Shadow AI y XAI)
A4: ID Caso | B4: Componente / Referencia | C4: Tipo de Prueba | D4: Prioridad | E4: Objetivo de la Prueba | F4: Datos de Entrada / Pasos de Ejecución | G4: Resultado Esperado | H4: Estado (QA) | I4: Observaciones / Evidencia
A5: TC-M6-01 | B5: Módulo 6 — Sección A.3.2 y B.6.4 (Prototipo Baja Fidelidad y XAI) | C5: Diseño UX / XAI | D5: Crítica | E5: Comprobar que el prototipo de baja fidelidad entregado en Fase 1 (Descubrimiento) incluya los 6 estados obligatorios antes de pasar a PoC. | F5: Inspeccionar las pantallas de la maqueta navegable presentada en el Gate G1. | G5: Incluye las 6 pantallas/flujos: 1. Respuesta correcta con al menos 1 patrón de XAI visual (citas, factores, casos similares, confianza visual o contrafactual). 2. Respuesta incierta. 3. Estado 'No sé' con alternativas. 4. Error detectable y corrección. 5. Flujo de override y feedback. 6. Baja confianza ('verifique antes de actuar'). | H5: PASS | I5: Verificado en conexión Parte A (A.3.2) y Parte B (B.6.4).
A6: TC-M6-02 | B6: Módulo 6 — Sección A.4.1 y B.8 (Gates de Calidad G0 a G5) | C6: Control de Gobernanza | D6: Crítica | E6: Validar que un proyecto no pueda cruzar el Gate G3 (Piloto -> Escalamiento) si tiene buenas métricas técnicas pero baja adopción. | F6: Simular solicitud de paso en Gate G3 con precisión del modelo en 92% (verde), pero con Penetración de usuarios = 45% (<60%) y sin runbooks de soporte L2/L3. | G6: • Decisión en Gate G3: RECHAZADO / Permanece en Fase 3 (Piloto). • G3 exige simultáneamente métricas técnicas y de adopción en verde (Penetración >= 60%), arquitectura validada y planes de soporte/adopción aprobados por Sponsor + Comité IA + Operación. | H6: PASS | I6: Tabla maestra de Gates verificada en Sección A.4.1.
A7: TC-M6-03 | B7: Módulo 6 — Sección A.7 (Matriz RACI Técnica) | C7: Segregación de Roles | D7: Media | E7: Auditar que la matriz RACI del proyecto respete los dos principios de asignación de responsabilidades. | F7: Revisar las 6 actividades de la tabla RACI adaptada al cliente. | G7: 1. Exactamente una 'A' (Aprobador final) por cada actividad. 2. En ninguna actividad el rol que tiene la 'A' es el mismo perfil que ejecuta la 'R' (Responsable). | H7: PASS | I7: Regla explícita en Sección A.7.
A8: TC-M6-04 | B8: Módulo 6 — Sección B.4.4 (Protocolo Shadow AI y Sandbox) | C8: Seguridad / Cambio | D8: Alta | E8: Verificar la implementación de los 3 componentes del protocolo de uso aceptable y las reglas del Sandbox de experimentación. | F8: 1. Revisar Lista Verde, Lista Roja y Vía de Solicitud. 2. Auditar los datasets utilizados dentro del Sandbox libre. | G8: 1. Lista Verde y Lista Roja publicadas. 2. Vía de solicitud para nuevas herramientas con SLA de respuesta < 4 semanas. 3. El Sandbox opera únicamente con datos sintéticos o anonimizados (cero PII o datos confidenciales reales). | H8: PASS | I8: Controles verificados en Sección B.4.4.
A9: TC-M6-05 | B9: Módulo 6 — Sección B.5 (Framework Miedo al Reemplazo) | C9: Ética / Comunicación | D9: Alta | E9: Auditar la clasificación honesta del modo de impacto humano (Automatización, Aumentación o Sustitución) y los 7 compromisos éticos. | F9: Revisar el plan de gestión del cambio de una iniciativa que reduce el headcount de un área operativa. | G9: • Se clasifica y comunica honestamente como 'Sustitución' (no como aumentación). • Incluye plan de transición individual, priorización de recolocación interna, transparencia algorítmica, no-discriminación y opción manual disponible sin penalización durante la transición. | H9: PASS | I9: Verificado en Secciones B.5.1 a B.5.4.
A10: TC-M6-06 | B10: Módulo 6 — Sección B.6.3 y B.8 (Métricas de Adopción y Override) | C10: Monitoreo Operativo | D10: Alta | E10: Detectar tanto el rechazo del sistema como el sesgo de automatización (Automation Bias) a través de la métrica de override humano. | F10: Evaluar dos escenarios en operación: • Escenario A: Override = 80%, Fallback manual = 55%, Penetración = 40%. • Escenario B: Override = 0.1% en un copiloto con tasa de error conocida del 10%. | G10: • Escenario A: Alerta por baja confianza y abandono hacia vía manual. • Escenario B: Alerta por Automation Bias (los usuarios aceptan sugerencias sin verificar); activa refuerzo de capacitación 'capacitar para desafiar'. | H10: PASS | I10: Métricas e indicador maestro verificados en Sección B.8.
